scholarpy/__init__.py
scholarpy/common.py
scholarpy/scholarpy.py
scholarpy-0.1.0.dist-info/LICENSE
scholarpy-0.1.0.dist-info/METADATA
scholarpy-0.1.0.dist-info/WHEEL
scholarpy-0.1.0.dist-info/dependency_links.txt
scholarpy-0.1.0.dist-info/top_level.txt
scholarpy-0.1.0.dist-info/RECORD
