Metadata-Version: 2.1
Name: scholarpy
Version: 0.1.0
Summary: A Python package for searching journal publications and researchers
Home-page: https://github.com/giswqs/scholarpy
Author: Qiusheng Wu
Author-email: giswqs@gmail.com
License: MIT license
Keywords: scholarpy
Platform: UNKNOWN
Classifier: Development Status :: 2 - Pre-Alpha
Classifier: Intended Audience :: Developers
Classifier: License :: OSI Approved :: MIT License
Classifier: Natural Language :: English
Classifier: Programming Language :: Python :: 3
Classifier: Programming Language :: Python :: 3.7
Classifier: Programming Language :: Python :: 3.8
Classifier: Programming Language :: Python :: 3.9
Requires-Python: >=3.7
License-File: LICENSE
